gym_simple_cliffworld/__init__.py
gym_simple_cliffworld/envs/__init__.py
gym_simple_cliffworld/envs/simple_cliffworld_v0.py
gym_simple_cliffworld-0.1.0.dist-info/LICENSE
gym_simple_cliffworld-0.1.0.dist-info/WHEEL
gym_simple_cliffworld-0.1.0.dist-info/METADATA
gym_simple_cliffworld-0.1.0.dist-info/RECORD
